splice_replace/__init__.py
splice_replace/splice_replace.py
tests/__init__.py
tests/test_splice_replace.py
splice_replace-0.1.2.dist-info/METADATA
splice_replace-0.1.2.dist-info/WHEEL
splice_replace-0.1.2.dist-info/entry_points.txt
splice_replace-0.1.2.dist-info/top_level.txt
splice_replace-0.1.2.dist-info/RECORD
