Metadata-Version: 2.1
Name: splice-replace
Version: 0.1.2
Summary: A utility to extract, process, and replace text in files based on line and column offsets.
Home-page: https://github.com/saltlakeryan/splice-replace
Author: Ryan Taylor
Classifier: Programming Language :: Python :: 3
Classifier: License :: OSI Approved :: MIT License
Classifier: Operating System :: OS Independent
